sqlite_explorer/__init__.py
sqlite_explorer/cli.py
sqlite_explorer/functions.py
sqlite_explorer/main.py
sqlite_explorer/src/__init__.py
sqlite_explorer/src/cli.py
sqlite_explorer/src/functions.py
sqlite_explorer-0.1.4.dist-info/LICENSE
sqlite_explorer-0.1.4.dist-info/METADATA
sqlite_explorer-0.1.4.dist-info/WHEEL
sqlite_explorer-0.1.4.dist-info/entry_points.txt
sqlite_explorer-0.1.4.dist-info/top_level.txt
sqlite_explorer-0.1.4.dist-info/RECORD
