Metadata-Version: 2.1
Name: sqlite-explorer
Version: 0.1.4
Summary: SQLiteExplorer is an application for manipulating SQLite databases from the command line.
Home-page: https://github.com/croketillo/sqlite-explorer
Author: Croketillo
Author-email: croketillo@gmail.com
License: GNU GENERAL PUBLIC LICENSE
Keywords: sqlite database databases sql
Platform: UNKNOWN
Classifier: Environment :: Console
Classifier: Intended Audience :: Developers
Classifier: License :: OSI Approved :: GNU General Public License v3 (GPLv3)
Classifier: Programming Language :: Python :: 3
Classifier: Programming Language :: Python :: 3.6
Classifier: Programming Language :: Python :: 3.7
Classifier: Programming Language :: Python :: 3.8
Classifier: Programming Language :: Python :: 3.9
Classifier: Topic :: Database
Classifier: Topic :: Software Development
Classifier: Topic :: Utilities
License-File: LICENSE
Requires-Dist: click
Requires-Dist: colorama
Requires-Dist: tabulate
